postprocess/__init__.py
postprocess/molecule_post_processor.py
postprocess-0.6.0.dist-info/METADATA
postprocess-0.6.0.dist-info/WHEEL
postprocess-0.6.0.dist-info/top_level.txt
postprocess-0.6.0.dist-info/RECORD
