Metadata-Version: 2.1
Name: postprocess
Version: 0.6.0
Summary: A brief description of the postprocess package
Classifier: Programming Language :: Python :: 3
Classifier: License :: OSI Approved :: MIT License
Classifier: Operating System :: OS Independent
Requires-Python: >=3.6
Requires-Dist: rdkit
